ffonons/__init__.py
ffonons/io.py
ffonons/plots.py
ffonons/run_phonon_maker.py
ffonons/analysis/__init__.py
ffonons/analysis/band_width.py
ffonons/analysis/check_phonondb_vasp_converged.py
ffonons/analysis/dos_mae.py
ffonons/analysis/imaginary_modes.py
ffonons/analysis/plot_dos_bs.py
ffonons/dbs/__init__.py
ffonons/dbs/fetch_phonondb_docs.py
ffonons/dbs/mp.py
ffonons/dbs/phonondb.py
ffonons-0.1.0.dist-info/METADATA
ffonons-0.1.0.dist-info/WHEEL
ffonons-0.1.0.dist-info/top_level.txt
ffonons-0.1.0.dist-info/RECORD
