Metadata-Version: 2.1
Name: ffonons
Version: 0.1.0
Summary: A Python package for benchmarking phonon predictions from ML force fields
Author-email: Janosh Riebesell <janosh.riebesell@gmail.com>
Project-URL: Homepage, https://janosh.github.io/ffonons
Project-URL: Repo, https://github.com/janosh/ffonons
Project-URL: Package, https://pypi.org/project/ffonons
Keywords: chemistry,force-fields,interatomic-potentials,machine-learning,materials-science,phonons,physics
Classifier: Intended Audience :: Science/Research
Classifier: License :: OSI Approved :: MIT License
Classifier: Operating System :: OS Independent
Classifier: Programming Language :: Python :: 3.11
Classifier: Topic :: Scientific/Engineering :: Artificial Intelligence
Classifier: Topic :: Scientific/Engineering :: Chemistry
Classifier: Topic :: Scientific/Engineering :: Physics
Requires-Python: >=3.11
Requires-Dist: matplotlib
Requires-Dist: numpy
Requires-Dist: pandas >=2.0.0
Requires-Dist: plotly
Requires-Dist: pymatgen
Requires-Dist: pymatviz[export-figs]
Requires-Dist: scikit-learn
Requires-Dist: scipy
Requires-Dist: tqdm
Provides-Extra: test
Requires-Dist: pytest ; extra == 'test'
Requires-Dist: pytest-cov ; extra == 'test'
